lifeguard_notification_google_chat/__init__.py
lifeguard_notification_google_chat/notifications.py
lifeguard_notification_google_chat/settings.py
lifeguard_notification_google_chat-0.0.9.dist-info/METADATA
lifeguard_notification_google_chat-0.0.9.dist-info/WHEEL
lifeguard_notification_google_chat-0.0.9.dist-info/top_level.txt
lifeguard_notification_google_chat-0.0.9.dist-info/RECORD
