Metadata-Version: 2.4
Name: lifeguard-notification-google-chat
Version: 0.0.9
Summary: Lifeguard integration with Google Chat
Home-page: https://github.com/LifeguardSystem/lifeguard-notification-google-chat
Author: Diego Rubin
Author-email: contact@diegorubin.dev
License: GPL2
Classifier: Development Status :: 3 - Alpha
Requires-Dist: lifeguard
Dynamic: author
Dynamic: author-email
Dynamic: classifier
Dynamic: home-page
Dynamic: license
Dynamic: requires-dist
Dynamic: summary
